lrxy/__init__.py
lrxy/__main__.py
lrxy/completions.py
lrxy/converter/__init__.py
lrxy/converter/lrc.py
lrxy/converter/main.py
lrxy/converter/srt.py
lrxy/converter/ttml.py
lrxy/converter/utils.py
lrxy/exceptions/__init__.py
lrxy/formats/__init__.py
lrxy/formats/filetype.py
lrxy/formats/id3.py
lrxy/formats/mp4.py
lrxy/formats/vorbis.py
lrxy/providers/__init__.py
lrxy/providers/applemusic.py
lrxy/providers/lrclib.py
lrxy/providers/musixmatch.py
lrxy/providers/qq.py
lrxy/providers/utils.py
lrxy/utils/__init__.py
lrxy/utils/audio.py
lrxy/utils/iter_files.py
lrxy-1.2.0.dist-info/licenses/LICENSE.md
lrxy-1.2.0.dist-info/METADATA
lrxy-1.2.0.dist-info/WHEEL
lrxy-1.2.0.dist-info/entry_points.txt
lrxy-1.2.0.dist-info/top_level.txt
lrxy-1.2.0.dist-info/RECORD
