Metadata-Version: 2.4
Name: lrxy
Version: 1.2.0
Summary: A synced lyric fetcher and embedder for music files
Author-email: pxeemo <pxeemo@gmail.com>
License:                     GNU GENERAL PUBLIC LICENSE
Project-URL: Repository, https://github.com/pxeemo/lrxy.git
Keywords: synced-lyrics,lyrics-fetcher
Requires-Python: >=3.10
License-File: LICENSE.md
Requires-Dist: requests
Requires-Dist: mutagen
Requires-Dist: argparse
Requires-Dist: argcomplete
Requires-Dist: lxml>=6.0.2
Dynamic: license-file
